MCP342x-0.3.3.dist-info/RECORD
MCP342x-0.3.3.dist-info/metadata.json
MCP342x-0.3.3.dist-info/WHEEL
MCP342x-0.3.3.dist-info/METADATA
MCP342x-0.3.3.dist-info/DESCRIPTION.rst
MCP342x-0.3.3.dist-info/top_level.txt
MCP342x/__init__.py
