Metadata-Version: 2.0
Name: MCP342x
Version: 0.3.3
Summary: Access Microchip MCP342x analogue to digital converters.
Home-page: https://github.com/stevemarple/python-MCP342x
Author: Steve Marple
Author-email: s.marple@lancaster.ac.uk
License: MIT
Platform: UNKNOWN
Classifier: Development Status :: 4 - Beta
Classifier: Intended Audience :: Education
Classifier: Intended Audience :: Science/Research
Classifier: Natural Language :: English
Classifier: License :: OSI Approved :: MIT License
Classifier: Operating System :: POSIX :: Linux
Classifier: Programming Language :: Python
Classifier: Programming Language :: Python :: 2
Classifier: Programming Language :: Python :: 2.7
Classifier: Programming Language :: Python :: 3
Classifier: Programming Language :: Python :: 3.3
Classifier: Topic :: Software Development :: Libraries :: Python Modules
Requires-Dist: smbus-cffi
